Metadata-Version: 1.0
Name: luko-rada-package-1
Version: 0.0.dev0
Summary: Rada with abstractfactory
Home-page: UNKNOWN
Author: Luko Kopach
Author-email: UNKNOWN
License: UNKNOWN
Keywords: abstract factory python itea
Platform: UNKNOWN
